{
    "nome": "Isabella Veigas",
    "idade": 25,
    "cpf": "672.320.029-20",
    "cns": "829253428317464",
    "rg": "10.368.614-9",
    "data_nasc": "19\/11\/1996",
    "sexo": "Feminino",
    "or_sexual": "Heterossexual",
    "mae": "Nicole Clarice",
    "pai": "Emanuel Henrique Caio Porto",
    "email": "eloaamandaporto-86@veraparodi.com.br",
    "cep": "85509-568",
    "endereco": "Rua Jacinto Zanardi",
    "numero": 517,
    "bairro": "São João",
    "cidade": "Pato Branco",
    "estado": "PR",
    "telefone_fixo": "(46) 2549-3214",
    "celular": "(46) 99415-8179",
    "altura": "1,80",
    "peso": 50,
    "tipo_sanguineo": "B+",
    "cor": "branco"
}